youtube_comments_scraper/__init__.py
youtube_comments_scraper/scraper.py
youtube_comments_scrapper-1.0.1.dist-info/LICENSE
youtube_comments_scrapper-1.0.1.dist-info/METADATA
youtube_comments_scrapper-1.0.1.dist-info/WHEEL
youtube_comments_scrapper-1.0.1.dist-info/top_level.txt
youtube_comments_scrapper-1.0.1.dist-info/RECORD
